{
  "version": "7",
  "dialect": "postgresql",
  "entries": [
    {
      "idx": 0,
      "version": "7",
      "when": 1776251970850,
      "tag": "0000_init",
      "breakpoints": true
    },
    {
      "idx": 1,
      "version": "7",
      "when": 1776253006004,
      "tag": "0001_seasons",
      "breakpoints": true
    },
    {
      "idx": 2,
      "version": "7",
      "when": 1776282896468,
      "tag": "0002_rich_invisible_woman",
      "breakpoints": true
    },
    {
      "idx": 3,
      "version": "7",
      "when": 1776284406582,
      "tag": "0003_grey_weapon_omega",
      "breakpoints": true
    },
    {
      "idx": 4,
      "version": "7",
      "when": 1776291717040,
      "tag": "0004_hot_punisher",
      "breakpoints": true
    }
  ]
}
